protoface/__init__.py
protoface-0.1.0.dist-info/METADATA
protoface-0.1.0.dist-info/WHEEL
protoface-0.1.0.dist-info/top_level.txt
protoface-0.1.0.dist-info/RECORD
