Metadata-Version: 2.1
Name: protoface
Version: 0.1.0
Summary: Protoface is a high-level GUI creation package based on Tkinter and designed to agilize interface prototyping.
Home-page: UNKNOWN
Author: Joel Romero Hernandez
Author-email: joelroihe@gmail.com
License: MIT
Platform: UNKNOWN
Classifier: Programming Language :: Python :: 3
Classifier: License :: OSI Approved :: MIT License
Classifier: Operating System :: OS Independent
Requires: tkinter
Requires-Python: >=3.7
